{
  "traits": [
    {
      "addPrice": 3500,
      "bypassLimit": false,
      "canAdd": true,
      "canRemove": true,
      "conflicts": [],
      "defName": "DrugDesire",
      "degree": -1,
      "description": "[PAWN_nameDef] verabscheut die Idee, sich an Chemikalien zu erfreuen. [PAWN_pronoun] vermeidet strikt Alkohol und Freizeitdrogen.",
      "name": "abstinenzler",
      "removePrice": 2550,
      "stats": []
    },
    {
      "addPrice": 3500,
      "bypassLimit": true,
      "canAdd": true,
      "canRemove": true,
      "conflicts": [],
      "defName": "Asexual",
      "degree": 0,
      "description": "{PAWN_nameDef} empfindet keinerlei sexuelles Verlangen.",
      "name": "asexuell",
      "removePrice": 2550,
      "stats": []
    },
    {
      "addPrice": 3500,
      "bypassLimit": false,
      "canAdd": true,
      "canRemove": true,
      "conflicts": [
        "habgierig",
        "eifersüchtig",
        "vielfraß"
      ],
      "defName": "Ascetic",
      "degree": 0,
      "description": "{PAWN_nameDef} hat auf körperliche Annehmlichkeiten und Vergnügen zugunsten eines einfachen, reinen Lebensstils verzichtet. {PAWN_pronoun} wird unglücklich, wenn {PAWN_possessive} Schlafzimmer zu beeindruckend ist. Des Weiteren verabscheut {PAWN_pronoun} ausgefallenes Essen und isst am liebsten roh. {PAWN_pronoun} beurteilt andere nie nach ihrem Aussehen.",
      "name": "asket",
      "removePrice": 2550,
      "stats": []
    },
    {
      "addPrice": 3500,
      "bypassLimit": false,
      "canAdd": true,
      "canRemove": true,
      "conflicts": [],
      "defName": "Abrasive",
      "degree": 0,
      "description": "{PAWN_nameDef} sagt immer genau das, was {PAWN_pronoun} denkt, besonders dann, wenn {PAWN_pronoun} selbst davon betroffen ist. {PAWN_possessive}e Art tendiert allerdings dazu, die Leute ständig zu verärgern.",
      "name": "aufreibend",
      "removePrice": 2550,
      "stats": []
    },
    {
      "addPrice": 3500,
      "bypassLimit": true,
      "canAdd": true,
      "canRemove": true,
      "conflicts": [],
      "defName": "Bisexual",
      "degree": 0,
      "description": "{PAWN_nameDef} fühlt sich sowohl zu Männern als auch zu Frauen romantisch hingezogen.",
      "name": "bisexuell",
      "removePrice": 2550,
      "stats": []
    },
    {
      "addPrice": 3500,
      "bypassLimit": false,
      "canAdd": true,
      "canRemove": true,
      "conflicts": [],
      "defName": "Bloodlust",
      "degree": 0,
      "description": "{PAWN_nameDef} bekommt einen Kick, wenn {PAWN_pronoun} jemanden verletzt. Außerdem stört {PAWN_pronoun} sich nicht am Anblick von Blut und Tod. Die Wahrscheinlichkeit, dass {PAWN_pronoun} eine Schlägerei beginnt, ist viermal so hoch wie bei anderen.",
      "name": "blutrünstig",
      "removePrice": 2550,
      "stats": []
    },
    {
      "addPrice": 3500,
      "bypassLimit": false,
      "canAdd": true,
      "canRemove": true,
      "conflicts": [],
      "defName": "NaturalMood",
      "degree": -2,
      "description": "[PAWN_nameDef] ist ständig betrübt. [PAWN_pronoun] hat Probleme damit, fröhlich zu bleiben, selbst wenn alles reibungslos läuft.",
      "name": "depressiv",
      "removePrice": 2550,
      "stats": []
    },
    {
      "addPrice": 3500,
      "bypassLimit": false,
      "canAdd": true,
      "canRemove": true,
      "conflicts": [
        "asket",
        "habgierig"
      ],
      "defName": "Jealous",
      "degree": 0,
      "description": "Für {PAWN_nameDef} ist es erniedrigend ein Schlafzimmer zu haben, das nicht so eindrucksvoll, wie das von jemand anderem ist. {PAWN_pronoun} bekommt einen Stimmungsabzug, wenn ein anderer Kolonist ein eindrucksvolleres Schlafzimmer hat.",
      "name": "eifersüchtig",
      "removePrice": 2550,
      "stats": []
    },
    {
      "addPrice": 3500,
      "bypassLimit": false,
      "canAdd": true,
      "canRemove": true,
      "conflicts": [],
      "defName": "Nerves",
      "degree": 2,
      "description": "Der Wille von [PAWN_nameDef] ist ein eisernes Schild. [PAWN_pronoun] macht weiter, auch wenn Andere schon lange aufgegeben haben.",
      "name": "eisernerwille",
      "removePrice": 2550,
      "stats": [
        "-18% Nervenzusammenbruchschwelle"
      ]
    },
    {
      "addPrice": 3500,
      "bypassLimit": false,
      "canAdd": true,
      "canRemove": true,
      "conflicts": [],
      "defName": "Beauty",
      "degree": -2,
      "description": "[PAWN_nameDef] ist unglaublich hässlich. [PAWN_possessive] Gesicht sieht wie eine Mischung aus dem Bild eines untalentierten Kindes, einem in Formaldehyd eingelegten verstümmelten Fötus und moderner Kunst aus. Andere müssen sich wirklich überwinden [PAWN_objective] bei einem Gespräch ins Gesicht zu sehen.",
      "name": "extremhässlich",
      "removePrice": 2550,
      "stats": [
        "-2.0 Attraktivität"
      ]
    },
    {
      "addPrice": 3500,
      "bypassLimit": false,
      "canAdd": true,
      "canRemove": true,
      "conflicts": [],
      "defName": "Industriousness",
      "degree": -2,
      "description": "[PAWN_nameDef] liebt es faul herumzulungern und hasst alles, was produktiv ist. [PAWN_pronoun] bewegt sich langsam und lässt sich leicht ablenken.",
      "name": "faul",
      "removePrice": 2550,
      "stats": [
        "-35% Geschwindigkeit alle Arbeiten"
      ]
    },
    {
      "addPrice": 3500,
      "bypassLimit": false,
      "canAdd": true,
      "canRemove": true,
      "conflicts": [],
      "defName": "Nerves",
      "degree": -2,
      "description": "[PAWN_nameDef] ist ständig nervös. [PAWN_pronoun] kann beim geringsten Stress in sich zusammenbrechen.",
      "name": "flatterhaft",
      "removePrice": 2550,
      "stats": [
        "+15% Nervenzusammenbruchschwelle"
      ]
    },
    {
      "addPrice": 3500,
      "bypassLimit": false,
      "canAdd": true,
      "canRemove": true,
      "conflicts": [],
      "defName": "Industriousness",
      "degree": 2,
      "description": "[PAWN_nameDef] lässt sich nicht leicht ablenken und erledigt dadurch [PAWN_possessive]e Aufgaben sehr viel schneller als durchschnittliche Personen.",
      "name": "fleißig",
      "removePrice": 2550,
      "stats": [
        "+35% Geschwindigkeit alle Arbeiten"
      ]
    },
    {
      "addPrice": 3500,
      "bypassLimit": false,
      "canAdd": true,
      "canRemove": true,
      "conflicts": [
        "aufreibend",
        "psychopath"
      ],
      "defName": "Kind",
      "degree": 0,
      "description": "{PAWN_nameDef} ist extrem freundlich. {PAWN_possessive}e besondere Fähigkeit ist es, mit freundlichen Worten jemandem den Tag zu versüßen. {PAWN_pronoun} beleidigt niemanden, und {PAWN_pronoun} beurteilt Menschen nie nach ihrem Aussehen.",
      "name": "freundlich",
      "removePrice": 2550,
      "stats": []
    },
    {
      "addPrice": 3500,
      "bypassLimit": false,
      "canAdd": true,
      "canRemove": true,
      "conflicts": [],
      "defName": "NaturalMood",
      "degree": 2,
      "description": "[PAWN_nameDef] ist von Natur aus fröhlich. Zu jeder Zeit, egal was passiert.",
      "name": "frohnatur",
      "removePrice": 2550,
      "stats": []
    },
    {
      "addPrice": 3500,
      "bypassLimit": false,
      "canAdd": true,
      "canRemove": true,
      "conflicts": [],
      "defName": "TorturedArtist",
      "degree": 0,
      "description": "{PAWN_nameDef} fühlt sich von anderen Menschen entfremdet und missverstanden. {PAWN_pronoun} hat einen ständigen Stimmungsmalus, aber es besteht die Chance (50%), dass {PAWN_pronoun} nach einem Nervenzusammenbruch eine kreative Inspiration erhält.",
      "name": "gequälterkünstler",
      "removePrice": 2550,
      "stats": []
    },
    {
      "addPrice": 3500,
      "bypassLimit": false,
      "canAdd": true,
      "canRemove": true,
      "conflicts": [],
      "defName": "Nimble",
      "degree": 0,
      "description": "{PAWN_nameDef} hat eine bemerkenswerte kinästhetische Intelligenz. {PAWN_pronoun} scheint mit einer außergewöhnlichen Eleganz um Gefahren herumzutanzen.",
      "name": "geschickt",
      "removePrice": 2550,
      "stats": [
        "+15.0 Nahkampfausweichchance",
        "x10% Fallenauslösungschance"
      ]
    },
    {
      "addPrice": 3500,
      "bypassLimit": false,
      "canAdd": true,
      "canRemove": true,
      "conflicts": [],
      "defName": "CreepyBreathing",
      "degree": 0,
      "description": "{PAWN_nameDef} atmet schwer und ist ständig am Schwitzen. Andere Leute finden das unheimlich.",
      "name": "gruseligeatmung",
      "removePrice": 2550,
      "stats": []
    },
    {
      "addPrice": 3500,
      "bypassLimit": false,
      "canAdd": true,
      "canRemove": true,
      "conflicts": [],
      "defName": "GreatMemory",
      "degree": 0,
      "description": "{PAWN_nameDef} hat ein fantastisches Gedächtnis für Details. {PAWN_possessive}e unbenutzten Fähigkeiten werden nur halb so schnell abgebaut wie bei anderen Personen.",
      "name": "gutesgedächtnis",
      "removePrice": 2550,
      "stats": []
    },
    {
      "addPrice": 3500,
      "bypassLimit": false,
      "canAdd": true,
      "canRemove": true,
      "conflicts": [
        "asket",
        "eifersüchtig"
      ],
      "defName": "Greedy",
      "degree": 0,
      "description": "{PAWN_nameDef} braucht ein sehr eindrucksvolles Schlafzimmer. {PAWN_pronoun} bekommt einen Stimmungsabzug, wenn {PAWN_pronoun} nicht bekommt, was {PAWN_pronoun} will.",
      "name": "habgierig",
      "removePrice": 2550,
      "stats": []
    },
    {
      "addPrice": 3500,
      "bypassLimit": false,
      "canAdd": true,
      "canRemove": true,
      "conflicts": [],
      "defName": "Industriousness",
      "degree": 1,
      "description": "[PAWN_nameDef] ist von Natur aus ein harter Arbeiter und wird Aufgaben schneller als die meisten anderen erledigen.",
      "name": "hartarbeitend",
      "removePrice": 2550,
      "stats": [
        "+20% Geschwindigkeit alle Arbeiten"
      ]
    },
    {
      "addPrice": 3500,
      "bypassLimit": false,
      "canAdd": true,
      "canRemove": true,
      "conflicts": [],
      "defName": "Beauty",
      "degree": -1,
      "description": "[PAWN_nameDef] ist nicht sonderlich schön, was einen subtilen negativen Einfluss auf andere hat.",
      "name": "hässlich",
      "removePrice": 2550,
      "stats": [
        "-1.0 Attraktivität"
      ]
    },
    {
      "addPrice": 3500,
      "bypassLimit": true,
      "canAdd": true,
      "canRemove": true,
      "conflicts": [],
      "defName": "Gay",
      "degree": 0,
      "description": "{PAWN_nameDef} fühlt sich zu Leuten {PAWN_possessive}es eigenen Geschlechts hingezogen.",
      "name": "homosexuell",
      "removePrice": 2550,
      "stats": []
    },
    {
      "addPrice": 3500,
      "bypassLimit": false,
      "canAdd": true,
      "canRemove": true,
      "conflicts": [],
      "defName": "Beauty",
      "degree": 1,
      "description": "[PAWN_nameDef] hat ein hübsches Gesicht, das die Menschen dazu veranlasst, [PAWN_objective] zu mögen.",
      "name": "hübsch",
      "removePrice": 2550,
      "stats": [
        "+1.0 Attraktivität"
      ]
    },
    {
      "addPrice": 3500,
      "bypassLimit": false,
      "canAdd": true,
      "canRemove": true,
      "conflicts": [],
      "defName": "SpeedOffset",
      "degree": 2,
      "description": "[PAWN_nameDef] geht immer, als wenn [PAWN_pronoun] es eilig hat. Andere schaffen es oft nicht, mit [PAWN_objective] mitzuhalten.",
      "name": "jogger",
      "removePrice": 2550,
      "stats": [
        "+0.40 Laufgeschwindigkeit"
      ]
    },
    {
      "addPrice": 3500,
      "bypassLimit": false,
      "canAdd": true,
      "canRemove": true,
      "conflicts": [],
      "defName": "Cannibal",
      "degree": 0,
      "description": "{PAWN_nameDef} wurde beigebracht, dass das Essen von Menschenfleisch schrecklich und falsch ist. Trotzdem hat {PAWN_pronoun} es einmal versucht... und es hat geschmeckt.",
      "name": "kannibale",
      "removePrice": 2550,
      "stats": []
    },
    {
      "addPrice": 3500,
      "bypassLimit": false,
      "canAdd": true,
      "canRemove": true,
      "conflicts": [
        "transhumanist"
      ],
      "defName": "BodyPurist",
      "degree": 0,
      "description": "{PAWN_nameDef} ist der Meinung, dass der menschliche Körper aus gutem Grund limitiert ist. {PAWN_pronoun} findet künstliche Körperteile unethisch und abstoßend.",
      "name": "körperpurist",
      "removePrice": 2550,
      "stats": []
    },
    {
      "addPrice": 3500,
      "bypassLimit": false,
      "canAdd": true,
      "canRemove": true,
      "conflicts": [],
      "defName": "QuickSleeper",
      "degree": 0,
      "description": "{PAWN_nameDef} braucht nicht so viel Schlaf wie eine durchschnittliche Person. Egal ob {PAWN_pronoun} im Bett oder auf dem Boden schläft, {PAWN_pronoun} wird in zwei Drittel der normalen Zeit komplett ausgeruht sein.",
      "name": "kurzschläfer",
      "removePrice": 2550,
      "stats": [
        "+50% Erholungsratenmultiplikator"
      ]
    },
    {
      "addPrice": 3500,
      "bypassLimit": false,
      "canAdd": true,
      "canRemove": true,
      "conflicts": [],
      "defName": "SpeedOffset",
      "degree": -1,
      "description": "[PAWN_nameDef] fällt immer hinter der Gruppe zurück, wo immer [PAWN_pronoun] auch hingeht.",
      "name": "lahmeente",
      "removePrice": 2550,
      "stats": [
        "-0.20 Laufgeschwindigkeit"
      ]
    },
    {
      "addPrice": 3500,
      "bypassLimit": false,
      "canAdd": true,
      "canRemove": true,
      "conflicts": [
        "zuklug"
      ],
      "defName": "SlowLearner",
      "degree": 0,
      "description": "{PAWN_nameDef} ist schwer von Begriff. {PAWN_pronoun} lernt viel langsamer als andere.",
      "name": "langsamerlerner",
      "removePrice": 2550,
      "stats": [
        "-75% Globaler Lernfaktor"
      ]
    },
    {
      "addPrice": 3500,
      "bypassLimit": false,
      "canAdd": true,
      "canRemove": true,
      "conflicts": [],
      "defName": "Masochist",
      "degree": 0,
      "description": "Für {PAWN_nameDef} ist Schmerz empfinden etwas Verbotenes und gleichzeitig Erregendes. {PAWN_pronoun} weiß nicht warum, aber {PAWN_pronoun} ist halt einfach anders verdrahtet.",
      "name": "masochist",
      "removePrice": 2550,
      "stats": []
    },
    {
      "addPrice": 3500,
      "bypassLimit": false,
      "canAdd": true,
      "canRemove": true,
      "conflicts": [],
      "defName": "DislikesMen",
      "degree": 0,
      "description": "{PAWN_nameDef} hat eine starke Abneigung zu allen Männern und misstraut ihnen.",
      "name": "misandrie",
      "removePrice": 2550,
      "stats": []
    },
    {
      "addPrice": 3500,
      "bypassLimit": false,
      "canAdd": true,
      "canRemove": true,
      "conflicts": [],
      "defName": "DislikesWomen",
      "degree": 0,
      "description": "{PAWN_nameDef} hat eine starke Abneigung zu allen Frauen und misstraut ihnen.",
      "name": "misogynie",
      "removePrice": 2550,
      "stats": []
    },
    {
      "addPrice": 3500,
      "bypassLimit": false,
      "canAdd": true,
      "canRemove": true,
      "conflicts": [],
      "defName": "NightOwl",
      "degree": 0,
      "description": "{PAWN_nameDef} liebt es nachts wach zu sein und am Tag zu schlafen.\n\n{PAWN_pronoun} bekommt einen Stimmungsbonus, wenn {PAWN_pronoun} nachts (23h-6h) wach ist und einen Stimmungsabzug, wenn {PAWN_pronoun} tagsüber (11h-18h) wach ist.\n\n{PAWN_pronoun} hat kein Problem damit, im Dunkeln zu sein.",
      "name": "nachteule",
      "removePrice": 2550,
      "stats": []
    },
    {
      "addPrice": 3500,
      "bypassLimit": false,
      "canAdd": true,
      "canRemove": true,
      "conflicts": [],
      "defName": "AnnoyingVoice",
      "degree": 0,
      "description": "{PAWN_nameDef} hat eine sehr schrille, nasale Stimme und tendiert dazu, sich in lauten aber unverständlichen Sätzen auszudrücken. Dies führt dazu, dass andere {PAWN_objective} nicht leiden können.",
      "name": "nervigestimme",
      "removePrice": 2550,
      "stats": []
    },
    {
      "addPrice": 3500,
      "bypassLimit": false,
      "canAdd": true,
      "canRemove": true,
      "conflicts": [],
      "defName": "Nerves",
      "degree": -1,
      "description": "[PAWN_nameDef] tendiert dazu, unter Stress zu zerbrechen.",
      "name": "nervös",
      "removePrice": 2550,
      "stats": [
        "+8% Nervenzusammenbruchschwelle"
      ]
    },
    {
      "addPrice": 3500,
      "bypassLimit": false,
      "canAdd": true,
      "canRemove": true,
      "conflicts": [],
      "defName": "Neurotic",
      "degree": 1,
      "description": "[PAWN_nameDef] mag es, wenn alle Dinge erledigt sind. [PAWN_pronoun] wird härter als Andere daran arbeiten, die Arbeit zu erledigen. Allerdings können [PAWN_possessive]e Nerven mit [PAWN_objective] durchgehen.",
      "name": "neurotisch",
      "removePrice": 2550,
      "stats": [
        "+20% Geschwindigkeit alle Arbeiten",
        "+8% Nervenzusammenbruchschwelle"
      ]
    },
    {
      "addPrice": 3500,
      "bypassLimit": false,
      "canAdd": true,
      "canRemove": true,
      "conflicts": [],
      "defName": "Nudist",
      "degree": 0,
      "description": "{PAWN_nameDef} genießt das Gefühl der Freiheit, das {PAWN_pronoun} hat, wenn {PAWN_pronoun} unbekleidet ist. {PAWN_pronoun} kann Kleidung tragen, aber ohne ist {PAWN_pronoun} glücklicher.",
      "name": "nudist",
      "removePrice": 2550,
      "stats": []
    },
    {
      "addPrice": 3500,
      "bypassLimit": false,
      "canAdd": true,
      "canRemove": true,
      "conflicts": [],
      "defName": "NaturalMood",
      "degree": 1,
      "description": "[PAWN_nameDef] ist von Natur aus optimistisch. Es ist schwer [PAWN_possessive]e Laune zu senken.",
      "name": "optimist",
      "removePrice": 2550,
      "stats": []
    },
    {
      "addPrice": 3500,
      "bypassLimit": false,
      "canAdd": true,
      "canRemove": true,
      "conflicts": [],
      "defName": "NaturalMood",
      "degree": -1,
      "description": "[PAWN_nameDef] ist von Natur aus pessimistisch. [PAWN_pronoun] tendiert dazu, die negative Seite des Lebens zu sehen.",
      "name": "pessimist",
      "removePrice": 2550,
      "stats": []
    },
    {
      "addPrice": 3500,
      "bypassLimit": false,
      "canAdd": true,
      "canRemove": true,
      "conflicts": [],
      "defName": "PsychicSensitivity",
      "degree": -1,
      "description": "[PAWN_nameDef] ist psychisch abgestumpft im Vergleich zu Anderen. [PAWN_pronoun] ist nicht sonderlich anfällig bei psychischen Phänomenen.",
      "name": "psychischabgestumpft",
      "removePrice": 2550,
      "stats": [
        "-50% Psychische Sensibilität"
      ]
    },
    {
      "addPrice": 3500,
      "bypassLimit": false,
      "canAdd": true,
      "canRemove": true,
      "conflicts": [],
      "defName": "PsychicSensitivity",
      "degree": 2,
      "description": "Das Gehirn von [PAWN_nameDef] ist wie eine hochsensible psychische Antenne. [PAWN_pronoun] ist sehr empfindlich gegenüber psychischen Phänomenen.",
      "name": "psychischhochsensibel",
      "removePrice": 2550,
      "stats": [
        "+80% Psychische Sensibilität"
      ]
    },
    {
      "addPrice": 3500,
      "bypassLimit": false,
      "canAdd": true,
      "canRemove": true,
      "conflicts": [],
      "defName": "PsychicSensitivity",
      "degree": 1,
      "description": "[PAWN_nameDef] ist außergewöhnlich empfindlich gegenüber psychischen Phänomenen.",
      "name": "psychischsensibel",
      "removePrice": 2550,
      "stats": [
        "+40% Psychische Sensibilität"
      ]
    },
    {
      "addPrice": 3500,
      "bypassLimit": false,
      "canAdd": true,
      "canRemove": true,
      "conflicts": [],
      "defName": "PsychicSensitivity",
      "degree": -2,
      "description": "Das Gehirn von [PAWN_nameDef] arbeitet auf einer anderen Frequenz als das der Anderen. [PAWN_pronoun] wird von psychischen Phänomenen nicht beeinflusst.",
      "name": "psychischtaub",
      "removePrice": 2550,
      "stats": [
        "-100% Psychische Sensibilität"
      ]
    },
    {
      "addPrice": 3500,
      "bypassLimit": false,
      "canAdd": true,
      "canRemove": true,
      "conflicts": [],
      "defName": "Psychopath",
      "degree": 0,
      "description": "{PAWN_nameDef} hat kein Mitgefühl. {PAWN_pronoun} stört sich nicht im Geringsten am Leid anderer. Es macht {PAWN_gender ? ihm : ihr} nichts aus, wenn andere getötet, tot liegen gelassen, eingesperrt oder in die Sklaverei verkauft werden - es sei denn, es betrifft {PAWN_objective} selbst. {PAWN_pronoun} bekommt keinen Stimmungsbonus bei sozialen Interaktionen.",
      "name": "psychopath",
      "removePrice": 2550,
      "stats": []
    },
    {
      "addPrice": 3500,
      "bypassLimit": false,
      "canAdd": true,
      "canRemove": true,
      "conflicts": [],
      "defName": "Pyromaniac",
      "degree": 0,
      "description": "{PAWN_nameDef} liebt Feuer. {PAWN_pronoun} wird nie ein Feuer löschen. Um Stress abzubauen wird {PAWN_pronoun} auch öfters in einen Feuerlege-Rausch verfallen. Das passiert umso häufiger, wenn {PAWN_possessive}e Laune niedrig ist.",
      "name": "pyromane",
      "removePrice": 2550,
      "stats": []
    },
    {
      "addPrice": 3500,
      "bypassLimit": false,
      "canAdd": true,
      "canRemove": true,
      "conflicts": [
        "sorgfältigerschütze",
        "schießwütig",
        "weichei"
      ],
      "defName": "Brawler",
      "degree": 0,
      "description": "{PAWN_nameDef} liebt es, wenn Kämpfe nah und persönlich sind. {PAWN_possessive}e Genauigkeit im Nahkampf ist unvergleichlich, aber {PAWN_pronoun} wird sehr unglücklich, wenn {PAWN_pronoun} eine Fernkampfwaffe tragen soll.",
      "name": "raufbold",
      "removePrice": 2550,
      "stats": [
        "+4.0 Nahkampftrefferchance"
      ]
    },
    {
      "addPrice": 3500,
      "bypassLimit": false,
      "canAdd": true,
      "canRemove": true,
      "conflicts": [],
      "defName": "DrugDesire",
      "degree": 2,
      "description": "[PAWN_nameDef] ist völlig fasziniert von chemischen Rauschmitteln. Der Konsum von Freizeitdrogen sorgt für gute Laune, während die Abstinenz mit der Zeit zu zunehmender Frustration und möglicherweise zu Drogenexzessen führt. [PAWN_pronoun] wird die Richtlinie, keine Freizeitdrogen zu konsumieren, ignorieren und mehr als ein normaler Mensch konsumieren.",
      "name": "rauschmittel-faszination",
      "removePrice": 2550,
      "stats": []
    },
    {
      "addPrice": 3500,
      "bypassLimit": false,
      "canAdd": true,
      "canRemove": true,
      "conflicts": [],
      "defName": "DrugDesire",
      "degree": 1,
      "description": "[PAWN_nameDef] hat ein ungewöhnliches Interesse an chemischen Rauschmitteln. [PAWN_pronoun] wird mehr davon konsumieren und, wenn [PAWN_pronoun] nicht schon von irgendeiner Droge abhängig und zufrieden ist, manchmal an gemeinsamen Drogenexzessen teilnehmen. [PAWN_pronoun] ignoriert Richtlinien, die den Verzicht auf Freizeitdrogen vorschreiben.",
      "name": "rauschmittel-interesse",
      "removePrice": 2550,
      "stats": []
    },
    {
      "addPrice": 3500,
      "bypassLimit": false,
      "canAdd": true,
      "canRemove": true,
      "conflicts": [
        "raufbold"
      ],
      "defName": "ShootingAccuracy",
      "degree": -1,
      "description": "Peng! Peng! Peng! [PAWN_nameDef] liebt es einfach abzudrücken. Im Vergleich mit anderen schießt [PAWN_pronoun] schneller, aber dafür auch mit geringerer Genauigkeit.",
      "name": "schießwütig",
      "removePrice": 2550,
      "stats": [
        "-50% Anvisierungsdauer",
        "-5.0 Fernkampfgenauigkeit (Personen)"
      ]
    },
    {
      "addPrice": 3500,
      "bypassLimit": false,
      "canAdd": true,
      "canRemove": true,
      "conflicts": [],
      "defName": "SpeedOffset",
      "degree": 1,
      "description": "[PAWN_nameDef] mag es dort hinzugehen, wo [PAWN_pronoun] hingeht. [PAWN_pronoun] geht schneller als die meisten Leute.",
      "name": "schnellergeher",
      "removePrice": 2550,
      "stats": [
        "+0.20 Laufgeschwindigkeit"
      ]
    },
    {
      "addPrice": 3500,
      "bypassLimit": false,
      "canAdd": true,
      "canRemove": true,
      "conflicts": [],
      "defName": "FastLearner",
      "degree": 0,
      "description": "{PAWN_nameDef} hat eine Begabung zum Lernen. {PAWN_pronoun} erlernt Sachen viel schneller als andere.",
      "name": "schnellerlerner",
      "removePrice": 2550,
      "stats": [
        "+75% Globaler Lernfaktor"
      ]
    },
    {
      "addPrice": 3500,
      "bypassLimit": false,
      "canAdd": true,
      "canRemove": true,
      "conflicts": [],
      "defName": "Immunity",
      "degree": -1,
      "description": "[PAWN_nameDef] hat ein schwaches Immunsystem. [PAWN_pronoun] wird häufiger als andere krank und bekommt häufig auch Krankheiten, die sonst niemand anderes in der Gemeinschaft hat.",
      "name": "schwachesimmunsystem",
      "removePrice": 2550,
      "stats": []
    },
    {
      "addPrice": 3500,
      "bypassLimit": false,
      "canAdd": true,
      "canRemove": true,
      "conflicts": [
        "raufbold"
      ],
      "defName": "ShootingAccuracy",
      "degree": 1,
      "description": "[PAWN_nameDef] nimmt sich mehr Zeit beim Anvisieren [PAWN_possessive]es Ziels. [PAWN_pronoun] schießt langsamer als andere, aber mit höherer Genauigkeit.",
      "name": "sorgfältigerschütze",
      "removePrice": 2550,
      "stats": [
        "+25% Anvisierungsdauer",
        "+5.0 Fernkampfgenauigkeit (Personen)"
      ]
    },
    {
      "addPrice": 3500,
      "bypassLimit": false,
      "canAdd": true,
      "canRemove": true,
      "conflicts": [],
      "defName": "Neurotic",
      "degree": 2,
      "description": "[PAWN_nameDef] ist ständig nervös, wenn es Dinge zu erledigen gibt. [PAWN_pronoun] wird viel härter als Andere daran arbeiten diesen Zustand abzustellen, aber [PAWN_pronoun] kann sehr leicht die Nerven verlieren.",
      "name": "starkneurotisch",
      "removePrice": 2550,
      "stats": [
        "+40% Geschwindigkeit alle Arbeiten",
        "+14% Nervenzusammenbruchschwelle"
      ]
    },
    {
      "addPrice": 3500,
      "bypassLimit": false,
      "canAdd": true,
      "canRemove": true,
      "conflicts": [],
      "defName": "Immunity",
      "degree": 1,
      "description": "[PAWN_nameDef] hat ein sehr gutes Immunsystem. [PAWN_pronoun] erreicht Immunitäten viel schneller als eine normale Person und kann Krankheiten überleben, die andere umbringen würden.",
      "name": "starkesimmunsystem",
      "removePrice": 2550,
      "stats": [
        "+30% Immunisierungsgeschwindigkeit"
      ]
    },
    {
      "addPrice": 3500,
      "bypassLimit": false,
      "canAdd": true,
      "canRemove": true,
      "conflicts": [],
      "defName": "Undergrounder",
      "degree": 0,
      "description": "{PAWN_nameDef} hat kein Bedürfnis, nach draußen zu gehen oder im Hellen zu sein. {PAWN_pronoun} wird sich nie eingeengt fühlen oder gar einen Lagerkoller bekommen, egal wie lange {PAWN_pronoun} drinnen oder im Dunkeln ist.",
      "name": "stubenhocker",
      "removePrice": 2550,
      "stats": []
    },
    {
      "addPrice": 3500,
      "bypassLimit": false,
      "canAdd": true,
      "canRemove": true,
      "conflicts": [],
      "defName": "Industriousness",
      "degree": -1,
      "description": "[PAWN_nameDef] ist ein bisschen träge.",
      "name": "träge",
      "removePrice": 2550,
      "stats": [
        "-20% Geschwindigkeit alle Arbeiten"
      ]
    },
    {
      "addPrice": 3500,
      "bypassLimit": false,
      "canAdd": true,
      "canRemove": true,
      "conflicts": [
        "körperpurist"
      ],
      "defName": "Transhumanist",
      "degree": 0,
      "description": "{PAWN_nameDef} fühlt sich begrenzt in {PAWN_possessive}em zerbrechlichen menschlichen Körper. {PAWN_pronoun} träumt oft davon {PAWN_possessive}e natürlichen Körperteile zu verbessern.",
      "name": "transhumanist",
      "removePrice": 2550,
      "stats": []
    },
    {
      "addPrice": 3500,
      "bypassLimit": false,
      "canAdd": true,
      "canRemove": true,
      "conflicts": [],
      "defName": "Nerves",
      "degree": 1,
      "description": "[PAWN_nameDef] besitzt große mentale Stärke und hält selbst solchem Stress stand, der Andere schon lange zerbrochen hätte.",
      "name": "unerschütterlich",
      "removePrice": 2550,
      "stats": [
        "-9% Nervenzusammenbruchschwelle"
      ]
    },
    {
      "addPrice": 3500,
      "bypassLimit": false,
      "canAdd": true,
      "canRemove": true,
      "conflicts": [
        "asket"
      ],
      "defName": "Gourmand",
      "degree": 0,
      "description": "{PAWN_nameDef} denkt ständig ans Essen. {PAWN_pronoun} wird schnell hungrig und bekommt gelegentlich den Drang, sich mit Essen vollzustopfen, auch wenn {PAWN_pronoun} eigentlich gar keinen Hunger hat.",
      "name": "vielfraß",
      "removePrice": 2550,
      "stats": []
    },
    {
      "addPrice": 3500,
      "bypassLimit": false,
      "canAdd": true,
      "canRemove": true,
      "conflicts": [
        "raufbold"
      ],
      "defName": "Wimp",
      "degree": 0,
      "description": "{PAWN_nameDef} ist schwach und feige. Jedes kleinste bisschen Schmerz führt dazu, dass {PAWN_pronoun} bewegungsunfähig wird.",
      "name": "weichei",
      "removePrice": 2550,
      "stats": [
        "-60% Schmerzschockschwelle"
      ]
    },
    {
      "addPrice": 3500,
      "bypassLimit": false,
      "canAdd": true,
      "canRemove": true,
      "conflicts": [],
      "defName": "Beauty",
      "degree": 2,
      "description": "[PAWN_nameDef] ist außergewöhnlich schön, mit einer exotischen und doch so vertrauten Gesichtsstruktur, sowie einem fesselnden Blick. Die Leute fahren schon auf [PAWN_objective] ab, bevor [PAWN_pronoun] überhaupt den Mund aufmacht.",
      "name": "wunderschön",
      "removePrice": 2550,
      "stats": [
        "+2.0 Attraktivität"
      ]
    },
    {
      "addPrice": 3500,
      "bypassLimit": false,
      "canAdd": true,
      "canRemove": true,
      "conflicts": [],
      "defName": "Tough",
      "degree": 0,
      "description": "{PAWN_nameDef} hat eine dicke Haut, zähes Fleisch und sehr stabile Knochen. {PAWN_pronoun} nimmt viel weniger Schaden als andere Personen und ist sehr schwer zu töten.",
      "name": "zäh",
      "removePrice": 2550,
      "stats": [
        "x50% Multiplikator eingehender Schaden"
      ]
    },
    {
      "addPrice": 3500,
      "bypassLimit": false,
      "canAdd": true,
      "canRemove": true,
      "conflicts": [
        "eisernerwille",
        "unerschütterlich",
        "nervös",
        "flatterhaft",
        "langsamerlerner"
      ],
      "defName": "TooSmart",
      "degree": 0,
      "description": "{PAWN_nameDef} ist zu intelligent für andere. {PAWN_pronoun} lernt wesentlich schneller als andere, kann aber auch ziemlich egozentrisch sein.",
      "name": "zuklug",
      "removePrice": 2550,
      "stats": [
        "+75% Globaler Lernfaktor",
        "+12% Nervenzusammenbruchschwelle"
      ]
    }
  ],
  "races": [
    {
      "defName": "Human",
      "enabled": true,
      "name": "mensch",
      "price": 2917
    }
  ]
}